{
  "sol": 933,
  "utc": "2028-01-28T12:55:33Z",
  "mars": {
    "ls": 142.1,
    "season": "Northern Summer",
    "temp_k": 212.5,
    "temp_c": -60.6,
    "pressure_pa": 662,
    "solar_wm2": 397,
    "dust_tau": 0.335,
    "wind_ms": 2.7,
    "lmst": 4.5
  },
  "events": [],
  "hazards": [],
  "comms": {
    "earth_delay_min": 11.7,
    "window_open": true,
    "bandwidth_kbps": 16
  },
  "terrain": {
    "regolith_hardness": 0.88,
    "water_ice_depth_m": 0.8,
    "surface_radiation_usv": 0.64
  },
  "frame_echo": {
    "prev_sol": 932,
    "thermal_efficiency_trend": "stable",
    "heating_demand_trend": "increasing",
    "insulation_status": "degrading"
  },
  "_hash": "8065ed4bfbb0e1f7"
}